pixi_to_conda_lock.py
pixi_to_conda_lock-0.4.3.dist-info/licenses/LICENSE
pixi_to_conda_lock-0.4.3.dist-info/METADATA
pixi_to_conda_lock-0.4.3.dist-info/WHEEL
pixi_to_conda_lock-0.4.3.dist-info/entry_points.txt
pixi_to_conda_lock-0.4.3.dist-info/top_level.txt
pixi_to_conda_lock-0.4.3.dist-info/RECORD
