Metadata-Version: 2.4
Name: pixi-to-conda-lock
Version: 0.4.3
Summary: pixi-to-conda-lock converts a pixi.lock file to a conda-lock.yml file.
Author-email: Bas Nijholt <bas@nijho.lt>
Project-URL: Homepage, https://github.com/basnijholt/pixi-to-conda-lock
Requires-Python: >=3.9
License-File: LICENSE
Requires-Dist: pyyaml
Requires-Dist: py-rattler
Provides-Extra: test
Requires-Dist: pytest; extra == "test"
Requires-Dist: pre-commit; extra == "test"
Requires-Dist: coverage; extra == "test"
Requires-Dist: pytest-cov; extra == "test"
Provides-Extra: rich
Requires-Dist: rich; extra == "rich"
Provides-Extra: docs
Dynamic: license-file
